tvi/solphit/base/__init__.py
tvi/solphit/base/arg_parsed.py
tvi/solphit/base/discovery.py
tvi/solphit/base/fs.py
tvi/solphit/base/jsonl.py
tvi/solphit/base/logging.py
tvi/solphit/base/timing.py
tvi_solphit_base-0.2.0.dist-info/licenses/LICENSE
tvi_solphit_base-0.2.0.dist-info/METADATA
tvi_solphit_base-0.2.0.dist-info/WHEEL
tvi_solphit_base-0.2.0.dist-info/top_level.txt
tvi_solphit_base-0.2.0.dist-info/RECORD
