Metadata-Version: 2.4
Name: tvi-solphit-base
Version: 0.2.0
Summary: Shared base utilities for the SolphIT stack.
Author: Tobias Hagenbeek
License: MIT License
Project-URL: Homepage, https://github.com/SolphIT/tvi-solphit-base
Project-URL: Changelog, https://github.com/SolphIT/tvi-solphit-base/blob/main/CHANGELOG.md
Keywords: logging,argparse,utilities,jsonl,filesystem
Classifier: Programming Language :: Python :: 3
Classifier: Programming Language :: Python :: 3.12
Classifier: License :: OSI Approved :: MIT License
Classifier: Operating System :: OS Independent
Requires-Python: >=3.9
License-File: LICENSE
Provides-Extra: test
Requires-Dist: pytest>=7.0; extra == "test"
Dynamic: license-file
